epr/__init__.py
epr/_epr.cpython-39-x86_64-linux-gnu.so
pyepr-1.2.0.dist-info/METADATA
pyepr-1.2.0.dist-info/WHEEL
pyepr-1.2.0.dist-info/top_level.txt
pyepr-1.2.0.dist-info/RECORD
pyepr-1.2.0.dist-info/licenses/LICENSE.txt
