Metadata-Version: 2.4
Name: pyepr
Version: 1.2.0
Summary: Python ENVISAT Product Reader API
Author-email: Antonio Valentino <antonio.valentino@tiscali.it>
License: GPL-3.0-or-later
Project-URL: Homepage, https://github.com/avalentino/pyepr
Project-URL: Documentation, https://pyepr.readthedocs.io
Project-URL: Repository, https://github.com/avalentino/pyepr.git
Project-URL: Changelog, https://github.com/avalentino/pyepr/blob/master/doc/NEWS.rst
Project-URL: Issues, https://github.com/avalentino/pyepr/issues
Keywords: satellite,reader,envisat
Classifier: Development Status :: 5 - Production/Stable
Classifier: Environment :: Other Environment
Classifier: Intended Audience :: Developers
Classifier: Intended Audience :: Science/Research
Classifier: Operating System :: MacOS :: MacOS X
Classifier: Operating System :: Microsoft :: Windows
Classifier: Operating System :: POSIX
Classifier: Programming Language :: Python
Classifier: Programming Language :: Python :: 3
Classifier: Programming Language :: Python :: 3 :: Only
Classifier: Programming Language :: Python :: Implementation :: CPython
Classifier: Programming Language :: Cython
Classifier: Topic :: Software Development :: Libraries
Classifier: Topic :: Scientific/Engineering
Classifier: Topic :: Scientific/Engineering :: GIS
Requires-Python: <4,>=3.9
License-File: LICENSE.txt
Requires-Dist: numpy>=1.7
Dynamic: license-file
